<products>
<product>
<id>1000000015</id>
<ecMallProductId>1000000015</ecMallProductId>
<name><![CDATA[비트&사과즙 100ml x30]]></name>
<basePrice>33800</basePrice>
<taxType>TAX</taxType>
<infoUrl><![CDATA[http://well-table.co.kr/goods/goods_view.php?inflow=naverPay&goodsNo=1000000015]]></infoUrl>
<imageUrl><![CDATA[http://www.well-table.co.kr/data/goods/18/07/28/1000000015/1000000015_main_017.jpg]]></imageUrl>
<status>ON_SALE</status>
<supplementSupport>false</supplementSupport>
<optionSupport>true</optionSupport>
<shippingPolicy>
<method>DELIVERY</method>
<groupId>2</groupId>
<conditionalFree>
<basePrice>50000</basePrice>
</conditionalFree>
<feePayType>PREPAYED</feePayType>
<feePrice>2500</feePrice>
<feeType>CONDITIONAL_FREE</feeType>
</shippingPolicy>
<option>
<optionItem>
<type>SELECT</type>
<name><![CDATA[비트&사과즙]]></name>
<value>
<id>S_786189b587c69bf10452838bf81106</id>
<text><![CDATA[비트&사과즙 100ml x30]]></text>
</value>
<value>
<id>S_7bcba4a9133b116ecba591fb24b9a8</id>
<text><![CDATA[비트&사과즙 100ml x60]]></text>
</value>
</optionItem>
<combination>
<manageCode>option300</manageCode>
<options>
<name><![CDATA[비트&사과즙]]></name>
<id>S_7bcba4a9133b116ecba591fb24b9a8</id>
</options>
<price>28000</price>
</combination>
<combination>
<manageCode>option299</manageCode>
<options>
<name><![CDATA[비트&사과즙]]></name>
<id>S_786189b587c69bf10452838bf81106</id>
</options>
<price>0</price>
</combination>
</option>
</product>
<product>
<id>1000000013</id>
<ecMallProductId>1000000013</ecMallProductId>
<name><![CDATA[건밥- 집 반찬&국 111종 골라담기]]></name>
<basePrice>3700</basePrice>
<taxType>TAX</taxType>
<infoUrl><![CDATA[http://well-table.co.kr/goods/goods_view.php?inflow=naverPay&goodsNo=1000000013]]></infoUrl>
<imageUrl><![CDATA[http://www.well-table.co.kr/data/goods/18/07/28/1000000013/1000000013_main_011.jpg]]></imageUrl>
<status>ON_SALE</status>
<supplementSupport>false</supplementSupport>
<optionSupport>true</optionSupport>
<shippingPolicy>
<method>DELIVERY</method>
<groupId>6</groupId>
<conditionalFree>
<basePrice>30000</basePrice>
</conditionalFree>
<feePayType>CASH_ON_DELIVERY</feePayType>
<feePrice>2500</feePrice>
<feeType>CONDITIONAL_FREE</feeType>
</shippingPolicy>
<option>
<optionItem>
<type>SELECT</type>
<name><![CDATA[건밥 반찬]]></name>
<value>
<id>S_fbe22cd309121436d76efc305c9dbc</id>
<text><![CDATA[01-가지볶음(200g)]]></text>
</value>
<value>
<id>S_fa3524af346d3b06fb791dc91bdf9d</id>
<text><![CDATA[02-고사리볶음(150g)]]></text>
</value>
<value>
<id>S_87f1b55840f8894d74231a16cc4bd9</id>
<text><![CDATA[03-고춧가루콩나물무침(150g)]]></text>
</value>
<value>
<id>S_eff8e91bdd5c78ec2d72979811b3bc</id>
<text><![CDATA[04-깻잎순무침(150g)]]></text>
</value>
<value>
<id>S_3fb30171afe4d7de7185ed00c277e0</id>
<text><![CDATA[05-느타리버섯볶음(150g)]]></text>
</value>
<value>
<id>S_d5e1a472a080842584dbe4563799f2</id>
<text><![CDATA[06-도라지볶음(150g)]]></text>
</value>
<value>
<id>S_58ddb5d3025e2f2f1ae5998e515504</id>
<text><![CDATA[07-무나물(150g)]]></text>
</value>
<value>
<id>S_e248eadb942117655ee049a0e1c15f</id>
<text><![CDATA[08-무생채(150g)]]></text>
</value>
<value>
<id>S_f81c47c10d2a1cdf7c131de2f634e0</id>
<text><![CDATA[09-미역줄기볶음(150g)]]></text>
</value>
<value>
<id>S_f2616b0ac88858e8f7734c24d059bb</id>
<text><![CDATA[10-숙주나물무침(150g)]]></text>
</value>
<value>
<id>S_48e9edaba4e0a74bb7963391badc45</id>
<text><![CDATA[11-시금치무침(150g)]]></text>
</value>
<value>
<id>S_31b1d124714ae7e3ff0d7d5c203fd8</id>
<text><![CDATA[12-시래기나물볶음(150g)]]></text>
</value>
<value>
<id>S_257868ebb13946ac0cbb9311334319</id>
<text><![CDATA[13-애호박볶음(200g)]]></text>
</value>
<value>
<id>S_97981746a9e269796504d604cc91f2</id>
<text><![CDATA[14-참나물무침(150g)]]></text>
</value>
<value>
<id>S_a8c89d4d3acb5a5b687d8daeba5dde</id>
<text><![CDATA[15-취나물무침(150g)]]></text>
</value>
<value>
<id>S_2f371f26bd6cabfa51d48e0faa6473</id>
<text><![CDATA[16-햄야채콩나물냉채(200g)]]></text>
</value>
<value>
<id>S_c2ddc4e74d089291981b14567b933a</id>
<text><![CDATA[17-간장어묵볶음(150g)]]></text>
</value>
<value>
<id>S_f7589042e7cc4c926fc5eb56fac90c</id>
<text><![CDATA[18-간장진미채볶음(100g)]]></text>
</value>
<value>
<id>S_05e3f5195fa7f4abf1cde6f114cece</id>
<text><![CDATA[19-감자채햄볶음(150g)]]></text>
</value>
<value>
<id>S_51eb8784701b45e403dd3487d7f311</id>
<text><![CDATA[20-건파래무침(200g)]]></text>
</value>
<value>
<id>S_5218dbedaa98333a4860578b709f64</id>
<text><![CDATA[21-고들빼기무침(200g)]]></text>
</value>
<value>
<id>S_522c381fb6b77df4ae369eed01f702</id>
<text><![CDATA[22-고추장더덕장아찌(200g)]]></text>
</value>
<value>
<id>S_c0198002711e7e95e89004bdcc9e55</id>
<text><![CDATA[23-고추장아찌(200g)]]></text>
</value>
<value>
<id>S_28490f310a0798cd92fb3609aa835e</id>
<text><![CDATA[24-고추장진미채무침(100g)]]></text>
</value>
<value>
<id>S_f225b642146c8b16877f593740b86f</id>
<text><![CDATA[25-김장아찌(100g)]]></text>
</value>
<value>
<id>S_c402d6ad890b1a20967cc7a9e16135</id>
<text><![CDATA[26-깻잎장아찌(200g)]]></text>
</value>
<value>
<id>S_91d55565d4710fbdc82c9d5e6d0a07</id>
<text><![CDATA[27-꽈리고추감자조림(150g)]]></text>
</value>
<value>
<id>S_3846cbe5c203b70596c59ce6e0516a</id>
<text><![CDATA[28-꽈리고추멸치고추장볶음(150g)]]></text>
</value>
<value>
<id>S_6f569cd6c14028657868a1181df869</id>
<text><![CDATA[29-꽈리고추멸치볶음(100g)]]></text>
</value>
<value>
<id>S_6a48f9287a8ba4d6b0edde46c2f1d3</id>
<text><![CDATA[30-달콤감자조림(200g)]]></text>
</value>
<value>
<id>S_f28b70883c25ffe5a6dd61d1357083</id>
<text><![CDATA[31-도라지오이무침(150g)]]></text>
</value>
<value>
<id>S_e2f5f8c1738ae817b56f2498f99070</id>
<text><![CDATA[32-동전문어조림(150g)]]></text>
</value>
<value>
<id>S_d5e0534837b5836c31481f7910c2f6</id>
<text><![CDATA[33-돼지고기장조림(200g)]]></text>
</value>
<value>
<id>S_bc6fc88595ede06c41b0f7ca338e11</id>
<text><![CDATA[34-두부조림(200g)]]></text>
</value>
<value>
<id>S_2fc730eef6853bd413a696b06c01a7</id>
<text><![CDATA[35-마늘장아찌(150g)]]></text>
</value>
<value>
<id>S_bec1314688a6fbc9211daaa3dc171c</id>
<text><![CDATA[36-마늘쫑멸치조림(150g)]]></text>
</value>
<value>
<id>S_a212dc9e183fa9f6f80899c7da311d</id>
<text><![CDATA[37-마늘쫑새우볶음(150g)]]></text>
</value>
<value>
<id>S_b89858013679cbd59937ab355bcba9</id>
<text><![CDATA[38-마늘쫑진미채무침(100g)]]></text>
</value>
<value>
<id>S_df671383f4c73ace70b5cf3a89a84b</id>
<text><![CDATA[39-매콤감자조림(200g)]]></text>
</value>
<value>
<id>S_502d0f355997c8333460ffd7c82698</id>
<text><![CDATA[40-메추리알장조림(200g)]]></text>
</value>
<value>
<id>S_3d2c962d415f7d21e7bc608cf35f88</id>
<text><![CDATA[41-멸치고추장볶음(100g)]]></text>
</value>
<value>
<id>S_c96021dac2a2c1568d4c272f99a9bb</id>
<text><![CDATA[42-멸치볶음(100g)]]></text>
</value>
<value>
<id>S_84272fee3e12acd4c831cba6e95271</id>
<text><![CDATA[43-무말랭이무침(150g)]]></text>
</value>
<value>
<id>S_85c7b382273e15d43ec2d735cced80</id>
<text><![CDATA[44-비엔나소세지야채볶음(200g)]]></text>
</value>
<value>
<id>S_8b095c64ad5ce9cb9976d1453d1930</id>
<text><![CDATA[45-빨간어묵볶음(200g)]]></text>
</value>
<value>
<id>S_3fadc0e78ede4b90191c7c6c5b8136</id>
<text><![CDATA[46-소고기모듬장조림(200g)]]></text>
</value>
<value>
<id>S_3aa1c12665819e5f0d4358bc9017b3</id>
<text><![CDATA[47-실채무침(80g)]]></text>
</value>
<value>
<id>S_d983fb3c6c702c514505d46743ec12</id>
<text><![CDATA[48-쌀게볶음(150g)]]></text>
</value>
<value>
<id>S_2771cf9a26718d05eaac7a99d52ee6</id>
<text><![CDATA[49-아삭이고추된장무침]]></text>
</value>
<value>
<id>S_1cb94dcdc41c32ffbd25e04faedcbf</id>
<text><![CDATA[50-우엉조림(200g)]]></text>
</value>
<value>
<id>S_f144c157a244093e6b23ee79b85a4b</id>
<text><![CDATA[51-연근조림(200g)]]></text>
</value>
<value>
<id>S_f4b641748271d36c93b5c14d631281</id>
<text><![CDATA[52-오이무침(200g)]]></text>
</value>
<value>
<id>S_3f88cbad9ed0b686ece829db4f53d5</id>
<text><![CDATA[53-잔멸치견과류볶음(100g)]]></text>
</value>
<value>
<id>S_a6b15c9d68e3b6c214c451cbe4bdbf</id>
<text><![CDATA[54-참치김치볶음(200g)]]></text>
</value>
<value>
<id>S_41f4170c7882392a69012e38e9dc4f</id>
<text><![CDATA[55-참치두부조림(200g)]]></text>
</value>
<value>
<id>S_de95772b6785c501c1136268e578fc</id>
<text><![CDATA[56-양념깨잎장아찌(200g)]]></text>
</value>
<value>
<id>S_c13ae718d3d170a1d5b62eed593398</id>
<text><![CDATA[57-콩자반(200g)]]></text>
</value>
<value>
<id>S_d8c9996f7fc70af44f6f4d6e7c33ef</id>
<text><![CDATA[58-해파리냉채(200g)]]></text>
</value>
<value>
<id>S_6350543901fc1d0f9b9c50bc78a1f1</id>
<text><![CDATA[59-황태채무침(150g)]]></text>
</value>
<value>
<id>S_c22d20672e591fa2f1c8b006f2e14d</id>
<text><![CDATA[60-미역초무침(150g)]]></text>
</value>
<value>
<id>S_a1768f80e27004a813bdc1412b46b4</id>
<text><![CDATA[61-달콤무조림(300g)]]></text>
</value>
<value>
<id>S_d1ddfd1881d6afaf1e8293f8bda0fb</id>
<text><![CDATA[62-건새우견과류볶음(100g)]]></text>
</value>
<value>
<id>S_9fe0219f80516496300a6091966cf8</id>
<text><![CDATA[63-감자샐러드(250g)]]></text>
</value>
<value>
<id>S_2f86d281d5ccb483b2dbc1735fbed9</id>
<text><![CDATA[64-스팸양파볶음(250g)]]></text>
</value>
<value>
<id>S_3b0c7d83ed65b0220ab2fe49652443</id>
<text><![CDATA[65-간장오징어볶음(250g)]]></text>
</value>
<value>
<id>S_6a2285d0f4c4e7f9558975447b38d9</id>
<text><![CDATA[66-메추리알곤약장조림(200g)]]></text>
</value>
<value>
<id>S_deff7f2115d38f66bc64d639c25746</id>
<text><![CDATA[67-오징어초무침(250g)]]></text>
</value>
<value>
<id>S_498ed5e3290e17a01e16829468afb8</id>
<text><![CDATA[68-꽈리고추찜(200g)]]></text>
</value>
<value>
<id>S_9bdd6f77a987f6dd3244373f59cd91</id>
<text><![CDATA[69-마늘쫑무침(150g)]]></text>
</value>
<value>
<id>S_883c269351be01222497ae4354c6a4</id>
<text><![CDATA[70-베이컨야채볶음(120g)]]></text>
</value>
<value>
<id>S_c658862bdb30b2bfa862f9c704f728</id>
<text><![CDATA[71-닭가슴살흑임자샐러드(250g)]]></text>
</value>
<value>
<id>S_e85bdfa4f728c0dc6db6bfebe91ddb</id>
<text><![CDATA[72-가리비젓무침(200g)]]></text>
</value>
<value>
<id>S_220b202a88f08f5bc45b017253ea03</id>
<text><![CDATA[73-갈치속젓무침(200g)]]></text>
</value>
<value>
<id>S_43460f6ef3a7a60eb1e556b3f79491</id>
<text><![CDATA[74-꼴뚜기젓무침(200g)]]></text>
</value>
<value>
<id>S_cf528d358bf85a2ce9b46cfe247a1a</id>
<text><![CDATA[75-낙지젓무침(200g)]]></text>
</value>
<value>
<id>S_ede03f0fe810894afac460dfda848c</id>
<text><![CDATA[76-어리굴젓무침(200g)]]></text>
</value>
<value>
<id>S_b50db5e6646ca1c9562ef7e2a79bee</id>
<text><![CDATA[77-조개젓무침(200g)]]></text>
</value>
<value>
<id>S_a5e3ceee888b2c7d5c68a227d1378e</id>
<text><![CDATA[78-창란젓무침(200g)]]></text>
</value>
<value>
<id>S_eabf68760990d37be81743e9ca445d</id>
<text><![CDATA[79-오징어젓무침(200g)]]></text>
</value>
<value>
<id>S_f77ed1d7346788fa66f6debe34311c</id>
<text><![CDATA[80-오징어비빔젓(200g)]]></text>
</value>
<value>
<id>S_0bcd3e22866f5dce302808936e2b72</id>
<text><![CDATA[81-계란말이(200g)]]></text>
</value>
<value>
<id>S_6d9e16203b023547191a69e77547f3</id>
<text><![CDATA[82-김치전(200g)]]></text>
</value>
<value>
<id>S_47a991184bff26ff534e823f23ed7f</id>
<text><![CDATA[83-동태전(200g)]]></text>
</value>
<value>
<id>S_9ba5e507505013632f21023d899876</id>
<text><![CDATA[84-애호박전(200g)]]></text>
</value>
<value>
<id>S_c7e42e34f76ef35db03f2c06feb743</id>
<text><![CDATA[85-버섯전(200g)]]></text>
</value>
<value>
<id>S_03ccf700b06962b39cf73d35579bc4</id>
<text><![CDATA[86-부추전(200g)]]></text>
</value>
<value>
<id>S_2ee8be6cfa6aa19ffc8937acc390fa</id>
<text><![CDATA[87-분홍소세지전(200g)]]></text>
</value>
<value>
<id>S_98f12a80ef65b38c6e2a18b732dad1</id>
<text><![CDATA[88-해물동그랑땡(200g)]]></text>
</value>
<value>
<id>S_5d3e4b269b75f7b9c603499ecdbd05</id>
<text><![CDATA[89-낙지볶음(250g)]]></text>
</value>
<value>
<id>S_b2a9c426b15dfc56ca0053ebd7f005</id>
<text><![CDATA[90-오징어볶음(250g)]]></text>
</value>
<value>
<id>S_edfbbf67b26fa1d3fdb5472601d38b</id>
<text><![CDATA[91-제육볶음(250g)]]></text>
</value>
<value>
<id>S_b076966593c649940b78cd3cbc34c7</id>
<text><![CDATA[92-짜장(300g)]]></text>
</value>
<value>
<id>S_60f2484b1abc6f9278ca5f22d29053</id>
<text><![CDATA[93-마파두부(300g)]]></text>
</value>
<value>
<id>S_2f6634cf94aa331f0ef1e56371d850</id>
<text><![CDATA[94-카레(300g)]]></text>
</value>
<value>
<id>S_b67dd2e4aab44a517a59f47ce351da</id>
<text><![CDATA[95-옛날잡채(300g)]]></text>
</value>
<value>
<id>S_ebba0810b08ef861f38aa6aaf6a72d</id>
<text><![CDATA[96-계란국(600g)]]></text>
</value>
<value>
<id>S_b7150f9fd4719a7c60f42957adb9aa</id>
<text><![CDATA[97-김치콩나물국(600g)]]></text>
</value>
<value>
<id>S_6d6bb103467ba7556b30efb265b96b</id>
<text><![CDATA[98-돼지고기김치찌개(600g)]]></text>
</value>
<value>
<id>S_b49cf23e7e3b67b7398828a40f45c7</id>
<text><![CDATA[99-바지락된장찌개(600g)]]></text>
</value>
<value>
<id>S_d1f2880beff261db9db65b7e29cd35</id>
<text><![CDATA[100-바지락미역국]]></text>
</value>
<value>
<id>S_4a6daf7ceb5e75ec659d053d637ddd</id>
<text><![CDATA[101-배춧국(600g)]]></text>
</value>
<value>
<id>S_9790b8a95de57f4bc01c261262a906</id>
<text><![CDATA[102-북엇국(600g)]]></text>
</value>
<value>
<id>S_31fc1c6395a5c36760b8e5b78af970</id>
<text><![CDATA[103-소고기뭇국(600g)]]></text>
</value>
<value>
<id>S_bac4c208c08a3d97803554defd3422</id>
<text><![CDATA[104-소고기미역국(600g)]]></text>
</value>
<value>
<id>S_698a64dd88744c88444131caabc147</id>
<text><![CDATA[105-시금치된장국(600g)]]></text>
</value>
<value>
<id>S_89d74d2e78beb73dead6698b9c4ea8</id>
<text><![CDATA[106-시래기들깨국(600g)]]></text>
</value>
<value>
<id>S_f9d809508b9242b26018cee2b39a83</id>
<text><![CDATA[107-아욱된장국(600g)]]></text>
</value>
<value>
<id>S_341cef6a5761310555c687453e3db2</id>
<text><![CDATA[108-오징어뭇국(600g)]]></text>
</value>
<value>
<id>S_a019563485df233ee4d8f17675ea40</id>
<text><![CDATA[109-콩나물국(600g)]]></text>
</value>
<value>
<id>S_2fff77b86db9bbf2278d92c9e446d7</id>
<text><![CDATA[110-육개장(600g)]]></text>
</value>
<value>
<id>S_2ee445a4af7dc75653a0f2105fe371</id>
<text><![CDATA[111-서리태콩물 (900ml)]]></text>
</value>
</optionItem>
<combination>
<manageCode>option104</manageCode>
<options>
<name><![CDATA[건밥 반찬]]></name>
<id>S_fbe22cd309121436d76efc305c9dbc</id>
</options>
<price>0</price>
</combination>
</option>
</product>
<product>
<id>1000000018</id>
<ecMallProductId>1000000018</ecMallProductId>
<name><![CDATA[노니 가루 & 노니]]></name>
<basePrice>26800</basePrice>
<taxType>TAX_FREE</taxType>
<infoUrl><![CDATA[http://well-table.co.kr/goods/goods_view.php?inflow=naverPay&goodsNo=1000000018]]></infoUrl>
<imageUrl><![CDATA[http://www.well-table.co.kr/data/goods/18/08/32/1000000018/1000000018_main_053.jpg]]></imageUrl>
<status>ON_SALE</status>
<supplementSupport>false</supplementSupport>
<optionSupport>true</optionSupport>
<shippingPolicy>
<method>DELIVERY</method>
<groupId>4</groupId>
<feePayType>FREE</feePayType>
<feePrice>0</feePrice>
<feeType>FREE</feeType>
</shippingPolicy>
<option>
<optionItem>
<type>SELECT</type>
<name><![CDATA[노니가루&노니 열매]]></name>
<value>
<id>S_716cf9beb32604e00ebba534f5f94d</id>
<text><![CDATA[01- 노니가루 250G X 2 + 열매 200G 1EA]]></text>
</value>
<value>
<id>S_f244774813a2d110fab0ae28455f5e</id>
<text><![CDATA[02-01- 노니가루 250G X 4 + 열매 200G 1EA]]></text>
</value>
</optionItem>
<combination>
<manageCode>option288</manageCode>
<options>
<name><![CDATA[노니가루&노니 열매]]></name>
<id>S_716cf9beb32604e00ebba534f5f94d</id>
</options>
<price>0</price>
</combination>
</option>
</product>
</products>
